pydub-0.24.1.dist-info/RECORD
pydub-0.24.1.dist-info/metadata.json
pydub-0.24.1.dist-info/WHEEL
pydub-0.24.1.dist-info/DESCRIPTION.rst
pydub-0.24.1.dist-info/top_level.txt
pydub-0.24.1.dist-info/METADATA
pydub/silence.py
pydub/effects.py
pydub/playback.py
pydub/audio_segment.py
pydub/pyaudioop.py
pydub/__init__.py
pydub/scipy_effects.py
pydub/generators.py
pydub/utils.py
pydub/exceptions.py
pydub/logging_utils.py
